phonon/__init__.py
phonon/animation.py
phonon/bz.py
phonon/cell.py
phonon/dynam.py
phonon/main.py
phonon/params.py
phonon/plot.py
phonon/thermal.py
phonon0K-0.0.17.data/scripts/phonon0K
phonon0K-0.0.17.dist-info/LICENSE
phonon0K-0.0.17.dist-info/METADATA
phonon0K-0.0.17.dist-info/WHEEL
phonon0K-0.0.17.dist-info/top_level.txt
phonon0K-0.0.17.dist-info/RECORD
