Metadata-Version: 2.1
Name: phonon0K
Version: 0.0.17
Summary: Harmonic phonon package
Home-page: https://gitlab.com/Coiana/phonon0K
Author: Gabriele Coiana
Author-email: gabriele.coiana17@imperial.ac.uk
License: UNKNOWN
Platform: UNKNOWN
Classifier: Programming Language :: Python :: 3
Classifier: License :: OSI Approved :: MIT License
Classifier: Operating System :: OS Independent
